<?xml version="1.0" encoding="UTF-8"?>
<mixins>
  <mixin target="b10f8718-7f39-4539-8a88-05046ca0a3d0">
    <!-- (G) entry_name: vay -->
    <!-- (G) part_of_speech: n -->
    <column name="definition_sv">klingonskans {v:sen:nolink}-ljud</column>
    <column name="notes_sv">Namnet på ett ljud, inte en skriven bokstav eller glyf.</column>
    <column name="examples_sv"></column>
    <column name="search_tags_sv"></column>
  </mixin>
  <mixin target="7a6a823d-7be6-42b4-b03c-13d6ed408396">
    <!-- (G) entry_name: va -->
    <!-- (G) part_of_speech: excl -->
    <column name="definition_sv">generellt invektiv</column>
    <column name="notes_sv">Detta är en förkortad form av {Qu'vatlh:excl}. [AUTOTRANSLATED]</column>
    <column name="examples_sv"></column>
    <column name="search_tags_sv"></column>
  </mixin>
  <mixin target="aafb9ccb-78fc-45cb-9474-094b95137234">
    <!-- (G) entry_name: vabDot -->
    <!-- (G) part_of_speech: adv -->
    <column name="definition_sv">även, tillochmed, också, likaså, dessutom</column>
    <column name="notes_sv">Detta används för att säga att något är oväntat eller överraskande eller motsatt, inte bara ytterligare. För det skulle man använda {je:adv}.[2] [AUTOTRANSLATED]</column>
    <column name="examples_sv"></column>
    <column name="search_tags_sv"></column>
  </mixin>
  <mixin target="ccf17ccc-a1a8-4f85-8fbd-a7d02b3d7dbd">
    <!-- (G) entry_name: vabDot Sovbe' targhwIj. -->
    <!-- (G) part_of_speech: sen:sp -->
    <column name="definition_sv">Även min targ kommer inte att veta. [AUTOTRANSLATED]</column>
    <column name="notes_sv"></column>
    <column name="examples_sv"></column>
    <column name="search_tags_sv"></column>
  </mixin>
  <mixin target="66c80c03-6966-434f-8b24-ae5360f009e1">
    <!-- (G) entry_name: vaD -->
    <!-- (G) part_of_speech: v:is -->
    <column name="definition_sv">vara böjlig, vara smidig</column>
    <column name="notes_sv">Det finns ett uttryck, {vaDjaj yaDDu'lIj:sen:nolink} "kan dina tår vara flexibla", vars betydelse är oklar, men som kan vara en önskan om lycka. [AUTOTRANSLATED]</column>
    <column name="examples_sv"></column>
    <column name="search_tags_sv"></column>
  </mixin>
  <mixin target="b8b3513d-aea2-4dc7-a858-232f27d6cc34">
    <!-- (G) entry_name: vagh -->
    <!-- (G) part_of_speech: n:1,num -->
    <column name="definition_sv">fem</column>
    <column name="notes_sv"></column>
    <column name="examples_sv"></column>
    <column name="search_tags_sv"></column>
  </mixin>
  <mixin target="894eeba6-7138-4cc1-8e25-e48ff27eed9c">
    <!-- (G) entry_name: vaghDIch -->
    <!-- (G) part_of_speech: n:num,deriv -->
    <column name="definition_sv">femte</column>
    <column name="notes_sv"></column>
    <column name="examples_sv"></column>
    <column name="search_tags_sv"></column>
  </mixin>
  <mixin target="b42be759-c8c5-427e-9c38-35bc7e9dea60">
    <!-- (G) entry_name: vaghmaH -->
    <!-- (G) part_of_speech: n:num,deriv -->
    <column name="definition_sv">femtio [AUTOTRANSLATED]</column>
    <column name="notes_sv"></column>
    <column name="examples_sv"></column>
    <column name="search_tags_sv"></column>
  </mixin>
  <mixin target="c8b84172-0592-4e70-b67c-700f166586a9">
    <!-- (G) entry_name: vagh -->
    <!-- (G) part_of_speech: n:2 -->
    <column name="definition_sv">femte tonen på den nonatoniska skalan</column>
    <column name="notes_sv"></column>
    <column name="examples_sv"></column>
    <column name="search_tags_sv"></column>
  </mixin>
  <mixin target="2136b58e-0600-4ba1-902a-ec2471e9767a">
    <!-- (G) entry_name: vagh reD mey' -->
    <!-- (G) part_of_speech: n:deriv -->
    <column name="definition_sv">pentagon [AUTOTRANSLATED]</column>
    <column name="notes_sv"></column>
    <column name="examples_sv"></column>
    <column name="search_tags_sv"></column>
  </mixin>
  <mixin target="c9ed6626-91a3-442e-9d67-a3e5b62e233e">
    <!-- (G) entry_name: vaH -->
    <!-- (G) part_of_speech: n -->
    <column name="definition_sv">hölster, slida, knivfodral</column>
    <column name="notes_sv">Detta kan faktiskt användas för allt som fungerar som ett skydd för något man lägger in i det.[3] [AUTOTRANSLATED]</column>
    <column name="examples_sv"></column>
    <column name="search_tags_sv"></column>
  </mixin>
  <mixin target="358d5a4c-7df1-4165-ae62-51dc7a6601c3">
    <!-- (G) entry_name: vaHbo' -->
    <!-- (G) part_of_speech: n -->
    <column name="definition_sv">lava</column>
    <column name="notes_sv"></column>
    <column name="examples_sv"></column>
    <column name="search_tags_sv"></column>
  </mixin>
  <mixin target="667c6a3b-9d3b-45af-a0a2-9afdf11a6f37">
    <!-- (G) entry_name: vaj -->
    <!-- (G) part_of_speech: adv -->
    <column name="definition_sv">så, därför, således, i så fall</column>
    <column name="notes_sv">Observera att detta inte är en konjunktion utan en adverbial. [AUTOTRANSLATED]</column>
    <column name="examples_sv"></column>
    <column name="search_tags_sv"></column>
  </mixin>
  <mixin target="aa88de76-4cb6-4145-b2fd-10800400cf87">
    <!-- (G) entry_name: vaj -->
    <!-- (G) part_of_speech: n -->
    <column name="definition_sv">krigare (som koncept)</column>
    <column name="notes_sv">Detta ord hänvisar till begreppet krigerskap (t.ex. "krigareanda" och så vidare). För att hänvisa till en person som är en krigare, använd {SuvwI':n}.[2] [AUTOTRANSLATED]</column>
    <column name="examples_sv"></column>
    <column name="search_tags_sv"></column>
  </mixin>
  <mixin target="98e4a9b3-4f84-430c-943f-0c9b7c3f18f4">
    <!-- (G) entry_name: vaj Duj -->
    <!-- (G) part_of_speech: n:deriv -->
    <column name="definition_sv">karaktärsstyrka [AUTOTRANSLATED]</column>
    <column name="notes_sv">Detta idiomatiska uttryck betyder bokstavligen "krigsfartyg" eller "krigareinstinkter" på grund av homofonin mellan {Duj:n:1} och {Duj:n:2}. [AUTOTRANSLATED]</column>
    <column name="examples_sv"></column>
    <column name="search_tags_sv"></column>
  </mixin>
  <mixin target="b3a56384-342c-4a14-9234-a9bac9e16428">
    <!-- (G) entry_name: vaj Duj chIj -->
    <!-- (G) part_of_speech: sen:idiom -->
    <column name="definition_sv">att ha styrka av karaktär [AUTOTRANSLATED]</column>
    <column name="notes_sv">Detta idiomatiska uttryck betyder bokstavligen "att navigera i ett krigsfartyg". [AUTOTRANSLATED]</column>
    <column name="examples_sv"></column>
    <column name="search_tags_sv"></column>
  </mixin>
  <mixin target="fff221a7-ab68-4916-bdb8-16db41a66b79">
    <!-- (G) entry_name: val -->
    <!-- (G) part_of_speech: v:is,klcp1 -->
    <column name="definition_sv">vara klipsk, vara smart, vara intelligent</column>
    <column name="notes_sv"></column>
    <column name="examples_sv"></column>
    <column name="search_tags_sv"></column>
  </mixin>
  <mixin target="3285d430-c1a6-4186-afab-25f696a3347a">
    <!-- (G) entry_name: valQav -->
    <!-- (G) part_of_speech: n:body -->
    <column name="definition_sv">iris (i ögat) [AUTOTRANSLATED]</column>
    <column name="notes_sv"></column>
    <column name="examples_sv"></column>
    <column name="search_tags_sv"></column>
  </mixin>
  <mixin target="122c8c4a-d54e-47d2-97e7-6cb10c1bfef6">
    <!-- (G) entry_name: valQIS -->
    <!-- (G) part_of_speech: n:name,fic -->
    <column name="definition_sv">Valkris</column>
    <column name="notes_sv"></column>
    <column name="examples_sv"></column>
    <column name="search_tags_sv"></column>
  </mixin>
  <mixin target="3c45b83b-e1eb-4375-ae96-b7f194b63819">
    <!-- (G) entry_name: valqe' -->
    <!-- (G) part_of_speech: n:anim -->
    <column name="definition_sv">fladdermus</column>
    <column name="notes_sv"></column>
    <column name="examples_sv"></column>
    <column name="search_tags_sv"></column>
  </mixin>
  <mixin target="b6d62b03-c085-40a5-a4b4-ef8a9f694559">
    <!-- (G) entry_name: valtIn -->
    <!-- (G) part_of_speech: n -->
    <column name="definition_sv">proton [AUTOTRANSLATED]</column>
    <column name="notes_sv"></column>
    <column name="examples_sv"></column>
    <column name="search_tags_sv"></column>
  </mixin>
  <mixin target="ef077c36-1f37-4f53-b029-f721419b73c4">
    <!-- (G) entry_name: van -->
    <!-- (G) part_of_speech: v:1,t_c,klcp1 -->
    <column name="definition_sv">hälsa, salutera</column>
    <column name="notes_sv"></column>
    <column name="examples_sv"></column>
    <column name="search_tags_sv"></column>
  </mixin>
  <mixin target="59434040-724d-4900-a39b-c90721b260d6">
    <!-- (G) entry_name: van -->
    <!-- (G) part_of_speech: v:2,t_c -->
    <column name="definition_sv">avsluta (en händelse, t.ex. resa, strid, sång)</column>
    <column name="notes_sv">Ämnet för detta verb är personen som får en händelse att avsluta. Objektet är händelsen som avslutas. Om händelsen avslutades för tidigt, använd {ghang:v} istället. Använd {Dor:v:2} istället för att beskriva slutet på en tidsperiod. [AUTOTRANSLATED]</column>
    <column name="examples_sv"></column>
    <column name="search_tags_sv"></column>
  </mixin>
  <mixin target="68d6e7f4-5635-41eb-b714-36b921697e62">
    <!-- (G) entry_name: van -->
    <!-- (G) part_of_speech: n -->
    <column name="definition_sv">hyllning, honnör, hälsning</column>
    <column name="notes_sv"></column>
    <column name="examples_sv"></column>
    <column name="search_tags_sv"></column>
  </mixin>
  <mixin target="87860454-4291-4f40-b870-2fc0f56d1cc7">
    <!-- (G) entry_name: vanDIroS -->
    <!-- (G) part_of_speech: n:place,fic -->
    <column name="definition_sv">Vandros IV</column>
    <column name="notes_sv">En planet i Gamma Quadrant. [AUTOTRANSLATED]</column>
    <column name="examples_sv"></column>
    <column name="search_tags_sv"></column>
  </mixin>
  <mixin target="127c9bbd-2b2b-410a-a6c0-b41493ef52d4">
    <!-- (G) entry_name: van'a' -->
    <!-- (G) part_of_speech: n:deriv -->
    <column name="definition_sv">pris, belöning</column>
    <column name="notes_sv"></column>
    <column name="examples_sv"></column>
    <column name="search_tags_sv"></column>
  </mixin>
  <mixin target="eabf5313-c453-42c5-a67d-c6becf258daa">
    <!-- (G) entry_name: van bom -->
    <!-- (G) part_of_speech: n:deriv -->
    <column name="definition_sv">hymn, lovsång</column>
    <column name="notes_sv"></column>
    <column name="examples_sv"></column>
    <column name="search_tags_sv"></column>
  </mixin>
  <mixin target="b9a613be-5083-4582-871c-ea2c88872893">
    <!-- (G) entry_name: van Hew -->
    <!-- (G) part_of_speech: n:deriv -->
    <column name="definition_sv">monument, minnesmärke (skulptur) [AUTOTRANSLATED]</column>
    <column name="notes_sv"></column>
    <column name="examples_sv"></column>
    <column name="search_tags_sv"></column>
  </mixin>
  <mixin target="bc3eedb5-8b3d-49b6-ac9e-c12dbeb4e072">
    <!-- (G) entry_name: van qach -->
    <!-- (G) part_of_speech: n:deriv -->
    <column name="definition_sv">monument, minnesmärke (byggnad) [AUTOTRANSLATED]</column>
    <column name="notes_sv"></column>
    <column name="examples_sv"></column>
    <column name="search_tags_sv"></column>
  </mixin>
  <mixin target="29620295-c4c1-4161-8fdc-efcd8970ad71">
    <!-- (G) entry_name: vang -->
    <!-- (G) part_of_speech: v:i,klcp1 -->
    <column name="definition_sv">agera, handla, göra (något)</column>
    <column name="notes_sv"></column>
    <column name="examples_sv"></column>
    <column name="search_tags_sv"></column>
  </mixin>
  <mixin target="73d127ba-eaab-46a3-875c-5f9df1d91a09">
    <!-- (G) entry_name: vangDI' tlhIngan SuvwI' ngoy' qorDu'Daj; vangDI' qorDu'Daj ngoy' tlhIngan SuvwI'. -->
    <!-- (G) part_of_speech: sen:phr -->
    <column name="definition_sv">Familjen av en Klingon krigare är ansvarig för sina handlingar, och han är ansvarig för deras. [AUTOTRANSLATED]</column>
    <column name="notes_sv"></column>
    <column name="examples_sv"></column>
    <column name="search_tags_sv"></column>
  </mixin>
  <mixin target="7526ea33-9153-4bc8-bad5-cf5e6cf8de7d">
    <!-- (G) entry_name: vaq -->
    <!-- (G) part_of_speech: v:t_c -->
    <column name="definition_sv">driva med, driva gäck med</column>
    <column name="notes_sv"></column>
    <column name="examples_sv"></column>
    <column name="search_tags_sv"></column>
  </mixin>
  <mixin target="862908ee-692a-465e-8a2e-f91d03ba359e">
    <!-- (G) entry_name: vaq'aj cha' -->
    <!-- (G) part_of_speech: n:place,fic -->
    <column name="definition_sv">Vaq'aj II [AUTOTRANSLATED]</column>
    <column name="notes_sv">Detta är en planet i Klingon Empire där infödda språk har överlevt tillsammans med Klingon. [AUTOTRANSLATED]</column>
    <column name="examples_sv"></column>
    <column name="search_tags_sv"></column>
  </mixin>
  <mixin target="d921986d-7071-4fb3-8620-f8dce2a79010">
    <!-- (G) entry_name: vaQ -->
    <!-- (G) part_of_speech: v:is -->
    <column name="definition_sv">vara aggressiv, vara effektiv, vara energisk, vara kraftfull</column>
    <column name="notes_sv">Detta ord användes ursprungligen för att beskriva vapen, men används nu också på människor. Det har starkt positiva konnotationer i slang.[2] [AUTOTRANSLATED]</column>
    <column name="examples_sv"></column>
    <column name="search_tags_sv"></column>
  </mixin>
  <mixin target="2748f070-329a-48c3-9884-0c32e1f06e49">
    <!-- (G) entry_name: var -->
    <!-- (G) part_of_speech: v:is -->
    <column name="definition_sv">var snål, var eländig [AUTOTRANSLATED]</column>
    <column name="notes_sv"></column>
    <column name="examples_sv"></column>
    <column name="search_tags_sv"></column>
  </mixin>
  <mixin target="7b033335-9d8b-40a1-84b2-ad54e9cc1f7e">
    <!-- (G) entry_name: varHa' -->
    <!-- (G) part_of_speech: v:is,deriv -->
    <column name="definition_sv">var generös [AUTOTRANSLATED]</column>
    <column name="notes_sv"></column>
    <column name="examples_sv"></column>
    <column name="search_tags_sv"></column>
  </mixin>
  <mixin target="4dfebb05-e88a-4a64-8b6c-aee9f15d4cc7">
    <!-- (G) entry_name: varghwI' -->
    <!-- (G) part_of_speech: n:being -->
    <column name="definition_sv">Förändring, grundare [AUTOTRANSLATED]</column>
    <column name="notes_sv">Detta hänvisar till en medlem i rasen med shapeshifters som leder Dominion ({ngup'a':n}). [AUTOTRANSLATED]</column>
    <column name="examples_sv"></column>
    <column name="search_tags_sv"></column>
  </mixin>
  <mixin target="cc208e93-3c45-4640-a6b6-9ee25d0aea8d">
    <!-- (G) entry_name: vaS -->
    <!-- (G) part_of_speech: n -->
    <column name="definition_sv">sal, mötessal</column>
    <column name="notes_sv"></column>
    <column name="examples_sv"></column>
    <column name="search_tags_sv"></column>
  </mixin>
  <mixin target="cc0011f1-24e3-441b-bc9b-f4c4e0b8d132">
    <!-- (G) entry_name: vaS'a' -->
    <!-- (G) part_of_speech: n:deriv -->
    <column name="definition_sv">Stora salen (Great Hall)</column>
    <column name="notes_sv">Detta är sätet för Klingon-regeringen. [AUTOTRANSLATED]</column>
    <column name="examples_sv"></column>
    <column name="search_tags_sv"></column>
  </mixin>
  <mixin target="19261993-cce2-4612-9d83-fa7ac60d2206">
    <!-- (G) entry_name: vaS -->
    <!-- (G) part_of_speech: v:is -->
    <column name="definition_sv">vara bred, bred [AUTOTRANSLATED]</column>
    <column name="notes_sv">Detta hänvisar till avstånd från sida till sida och har inte de metaforiska betydelserna som "brett ämne" eller "brett spektrum av åsikter", och det används inte heller för att "i full utsträckning" såsom "ögon breda" öppna". [AUTOTRANSLATED]</column>
    <column name="examples_sv"></column>
    <column name="search_tags_sv"></column>
  </mixin>
  <mixin target="8a996029-9606-4404-ba79-018056fae28f">
    <!-- (G) entry_name: vatlh -->
    <!-- (G) part_of_speech: n:num -->
    <column name="definition_sv">hundra (nummerbildande element)</column>
    <column name="notes_sv"></column>
    <column name="examples_sv"></column>
    <column name="search_tags_sv"></column>
  </mixin>
  <mixin target="5179e3f2-d0b1-46d8-ba1b-0ff3e2fdcd2b">
    <!-- (G) entry_name: vatlhbIp -->
    <!-- (G) part_of_speech: n:num,deriv -->
    <column name="definition_sv">tio miljoner (nummerbildande element) [AUTOTRANSLATED]</column>
    <column name="notes_sv"></column>
    <column name="examples_sv"></column>
    <column name="search_tags_sv"></column>
  </mixin>
  <mixin target="38ded290-8ee5-45b6-840b-c774a28b2e6b">
    <!-- (G) entry_name: vatlhSaghan -->
    <!-- (G) part_of_speech: n:num,deriv -->
    <column name="definition_sv">hundra miljarder (nummerbildande element) [AUTOTRANSLATED]</column>
    <column name="notes_sv"></column>
    <column name="examples_sv"></column>
    <column name="search_tags_sv"></column>
  </mixin>
  <mixin target="873a9fef-de9f-4dcd-9b71-ef6b456944b8">
    <!-- (G) entry_name: vatlhvI' -->
    <!-- (G) part_of_speech: n -->
    <column name="definition_sv">procent</column>
    <column name="notes_sv"></column>
    <column name="examples_sv"></column>
    <column name="search_tags_sv"></column>
  </mixin>
  <mixin target="58595d9e-1226-453b-a3af-1f61b01465ea">
    <!-- (G) entry_name: vatlh'uy' -->
    <!-- (G) part_of_speech: n:num,deriv -->
    <column name="definition_sv">hundra miljoner (nummerbildande element) [AUTOTRANSLATED]</column>
    <column name="notes_sv"></column>
    <column name="examples_sv"></column>
    <column name="search_tags_sv"></column>
  </mixin>
  <mixin target="08129a24-075a-499a-8c90-408c9d343c0c">
    <!-- (G) entry_name: vatlh DIS poH -->
    <!-- (G) part_of_speech: n:deriv -->
    <column name="definition_sv">sekel</column>
    <column name="notes_sv">För att ange "århundraden sedan" eller "århundraden från och med nu" används {ret:n} och {pIq:n} i stället för {poH:n}, respektive.[3] [AUTOTRANSLATED]</column>
    <column name="examples_sv"></column>
    <column name="search_tags_sv"></column>
  </mixin>
  <mixin target="d6494acb-572d-4eca-96ff-a24be3ad39d9">
    <!-- (G) entry_name: vatlh -->
    <!-- (G) part_of_speech: v:i -->
    <column name="definition_sv">spole [AUTOTRANSLATED]</column>
    <column name="notes_sv"></column>
    <column name="examples_sv"></column>
    <column name="search_tags_sv"></column>
  </mixin>
  <mixin target="81c85499-b185-44c5-8453-dbcb01f21799">
    <!-- (G) entry_name: vatlhmoH -->
    <!-- (G) part_of_speech: v:t_c,deriv -->
    <column name="definition_sv">rulla ihop (en rulla) [AUTOTRANSLATED]</column>
    <column name="notes_sv"></column>
    <column name="examples_sv"></column>
    <column name="search_tags_sv"></column>
  </mixin>
  <mixin target="828e42b8-958a-4781-857a-d1c12103b8b6">
    <!-- (G) entry_name: vav -->
    <!-- (G) part_of_speech: n:being,klcp1 -->
    <column name="definition_sv">far, fader</column>
    <column name="notes_sv">Syskon till en {vav:n:nolink} är {tennuS:n} och {'e'mam:n}. [AUTOTRANSLATED]</column>
    <column name="examples_sv"></column>
    <column name="search_tags_sv"></column>
  </mixin>
  <mixin target="5e0f1103-bac9-465c-84c6-f09e00b2f657">
    <!-- (G) entry_name: vavoy -->
    <!-- (G) part_of_speech: n:being,deriv -->
    <column name="definition_sv">pappa [AUTOTRANSLATED]</column>
    <column name="notes_sv"></column>
    <column name="examples_sv"></column>
    <column name="search_tags_sv"></column>
  </mixin>
  <mixin target="5dcebb80-91f9-484f-ad20-6aca5b69febe">
    <!-- (G) entry_name: vavnI' -->
    <!-- (G) part_of_speech: n:being,klcp1 -->
    <column name="definition_sv">farfar, morfar</column>
    <column name="notes_sv"></column>
    <column name="examples_sv"></column>
    <column name="search_tags_sv"></column>
  </mixin>
  <mixin target="c382ddee-d9ea-4761-8d8b-33c418745804">
    <!-- (G) entry_name: vaw -->
    <!-- (G) part_of_speech: v:is -->
    <column name="definition_sv">vara ambitiös, bestämd, motiverad [AUTOTRANSLATED]</column>
    <column name="notes_sv">Observera att detta kan hänvisa till en ambitiös person, men inte en ambitiös uppgift.

Till skillnad från {pIl:v} avser detta självmotivering. [AUTOTRANSLATED]</column>
    <column name="examples_sv"></column>
    <column name="search_tags_sv"></column>
  </mixin>
  <mixin target="a20b5cc2-8f93-44bc-9986-94c634f2f3ab">
    <!-- (G) entry_name: vay -->
    <!-- (G) part_of_speech: v:t_c -->
    <column name="definition_sv">slåss, strida (mellanstor vildsinthet)</column>
    <column name="notes_sv">I stigande graden av våldsamhet är verben som används för att beskriva militära konfrontationer: {Qor:v}, {tlhaS:v}, {vay:v:nolink}, {lul:v}, {Hargh:v}. [AUTOTRANSLATED]</column>
    <column name="examples_sv"></column>
    <column name="search_tags_sv"></column>
  </mixin>
  <mixin target="3a0640c9-b043-4bf7-9480-74865f63010a">
    <!-- (G) entry_name: vayya' -->
    <!-- (G) part_of_speech: n -->
    <column name="definition_sv">likbent triangel [AUTOTRANSLATED]</column>
    <column name="notes_sv"></column>
    <column name="examples_sv"></column>
    <column name="search_tags_sv"></column>
  </mixin>
  <mixin target="9770c046-3c62-47d3-9108-f565063b9314">
    <!-- (G) entry_name: vay' -->
    <!-- (G) part_of_speech: n:klcp1 -->
    <column name="definition_sv">något, någon, någonting</column>
    <column name="notes_sv"></column>
    <column name="examples_sv"></column>
    <column name="search_tags_sv"></column>
  </mixin>
  <mixin target="1d5fbe92-824a-4b53-8c2b-34fa3c8ca597">
    <!-- (G) entry_name: vay' DaneHbogh yIchargh. -->
    <!-- (G) part_of_speech: sen:phr -->
    <column name="definition_sv">Erövra vad du önskar. [AUTOTRANSLATED]</column>
    <column name="notes_sv"></column>
    <column name="examples_sv"></column>
    <column name="search_tags_sv"></column>
  </mixin>
  <mixin target="5eb7a04a-5426-4583-87c7-37956d190d65">
    <!-- (G) entry_name: vay' DaghIjlaHchugh bIHoSghaj. -->
    <!-- (G) part_of_speech: sen:phr -->
    <column name="definition_sv">Rädsla är makt. [AUTOTRANSLATED]</column>
    <column name="notes_sv"></column>
    <column name="examples_sv"></column>
    <column name="search_tags_sv"></column>
  </mixin>
  <mixin target="e2b5ad05-ba5c-4f09-b845-636fd3a9ef06">
    <!-- (G) entry_name: vay' DalarghDI' yIqaw. -->
    <!-- (G) part_of_speech: sen:phr -->
    <column name="definition_sv">Kom ihåg doften. [AUTOTRANSLATED]</column>
    <column name="notes_sv">Detta betyder "Lär dig av dina erfarenheter." [AUTOTRANSLATED]</column>
    <column name="examples_sv"></column>
    <column name="search_tags_sv"></column>
  </mixin>
  <mixin target="901f1c1a-7a97-434d-b9ca-2b64d17bd413">
    <!-- (G) entry_name: va'chum -->
    <!-- (G) part_of_speech: n -->
    <column name="definition_sv">svamp (verktyg) [AUTOTRANSLATED]</column>
    <column name="notes_sv"></column>
    <column name="examples_sv"></column>
    <column name="search_tags_sv"></column>
  </mixin>
  <mixin target="40aba4c3-5dc0-4688-84ce-2dbbec29c5d1">
    <!-- (G) entry_name: va'nuch -->
    <!-- (G) part_of_speech: n:body -->
    <column name="definition_sv">häl</column>
    <column name="notes_sv"></column>
    <column name="examples_sv"></column>
    <column name="search_tags_sv"></column>
  </mixin>
  <mixin target="02e9f3c1-3e07-4901-960d-bbdda9bd1b42">
    <!-- (G) entry_name: veb -->
    <!-- (G) part_of_speech: v:is -->
    <column name="definition_sv">vara nästa, vara efterföljande (i ordning, serie)</column>
    <column name="notes_sv">För att hänvisa till nästa dag, månad eller år, överväga att använda {leS:n}, {waQ:n} respektive {nem:n}. [AUTOTRANSLATED]</column>
    <column name="examples_sv"></column>
    <column name="search_tags_sv"></column>
  </mixin>
  <mixin target="d5431575-ea6b-44b1-b75c-ce0ff2b8bd94">
    <!-- (G) entry_name: vech -->
    <!-- (G) part_of_speech: v:t_c -->
    <column name="definition_sv">kors, spänn [AUTOTRANSLATED]</column>
    <column name="notes_sv">Detta innebär att spänna eller korsa i stationär mening, som till exempel en bro som sträcker sig över en flod, två fingrar som korsar eller en rand målad tvärs över vägen. [AUTOTRANSLATED][1]</column>
    <column name="examples_sv"></column>
    <column name="search_tags_sv"></column>
  </mixin>
  <mixin target="831fb96e-c42f-4072-8479-51f87cf4ab9c">
    <!-- (G) entry_name: veD -->
    <!-- (G) part_of_speech: n:body -->
    <column name="definition_sv">pälshår, lurv</column>
    <column name="notes_sv"></column>
    <column name="examples_sv"></column>
    <column name="search_tags_sv"></column>
  </mixin>
  <mixin target="390122f6-6e41-4c96-baff-cd71eb4e05f9">
    <!-- (G) entry_name: veDDIr -->
    <!-- (G) part_of_speech: n:deriv -->
    <column name="definition_sv">päls (skinn där håret lämnats kvar)</column>
    <column name="notes_sv">Plural av detta ord är {veDDIrmey:n:nolink} snarare än {veDDIrDu':n:nolink}.[1; 2] [AUTOTRANSLATED]</column>
    <column name="examples_sv"></column>
    <column name="search_tags_sv"></column>
  </mixin>
  <mixin target="25696259-660e-4af4-99e6-a2628bc91fcc">
    <!-- (G) entry_name: vegh -->
    <!-- (G) part_of_speech: v:t_c -->
    <column name="definition_sv">gå igenom (en öppen dörr, tunnel etc.)</column>
    <column name="notes_sv"></column>
    <column name="examples_sv"></column>
    <column name="search_tags_sv"></column>
  </mixin>
  <mixin target="c38e1e53-9322-4605-83fb-41f16458870c">
    <!-- (G) entry_name: veH -->
    <!-- (G) part_of_speech: n -->
    <column name="definition_sv">gräns, gränslinje</column>
    <column name="notes_sv"></column>
    <column name="examples_sv"></column>
    <column name="search_tags_sv"></column>
  </mixin>
  <mixin target="8eee954e-9f23-4d24-b772-aa4c4594f344">
    <!-- (G) entry_name: veH tIn -->
    <!-- (G) part_of_speech: n:deriv -->
    <column name="definition_sv">Stora Barriären</column>
    <column name="notes_sv"></column>
    <column name="examples_sv"></column>
    <column name="search_tags_sv"></column>
  </mixin>
  <mixin target="af47614d-98fd-4f4e-bb3b-0e0f2834eb8a">
    <!-- (G) entry_name: veH Qav 'oH logh'e' -->
    <!-- (G) part_of_speech: sen:phr -->
    <column name="definition_sv">"Space: den sista gränsen" [AUTOTRANSLATED]</column>
    <column name="notes_sv"></column>
    <column name="examples_sv"></column>
    <column name="search_tags_sv"></column>
  </mixin>
  <mixin target="469b2193-1298-43ff-871b-0f111b2dce54">
    <!-- (G) entry_name: vel -->
    <!-- (G) part_of_speech: v:t_c -->
    <column name="definition_sv">täcka, klä, övertäcka, mattbelägga</column>
    <column name="notes_sv">Ämnet täcker, medan föremålet är täckt.

Detta verb används för att beskriva läggningen av en matta. Den som lägger en matta kallas {velwI':n}. [AUTOTRANSLATED]</column>
    <column name="examples_sv"></column>
    <column name="search_tags_sv"></column>
  </mixin>
  <mixin target="064ef54c-ff5f-4ad1-b3a7-c6acc9a83b10">
    <!-- (G) entry_name: velwI' -->
    <!-- (G) part_of_speech: n:being,deriv -->
    <column name="definition_sv">mattlager (person) [AUTOTRANSLATED]</column>
    <column name="notes_sv"></column>
    <column name="examples_sv"></column>
    <column name="search_tags_sv"></column>
  </mixin>
  <mixin target="18cdb4ba-a2b1-4135-a37a-b0e15f4a2999">
    <!-- (G) entry_name: velqa' -->
    <!-- (G) part_of_speech: n -->
    <column name="definition_sv">replik, kopia</column>
    <column name="notes_sv">I {Klingon Monopoly:src} benämns "Chancellor's Cane Replica" {Qang naQ velqa':n:nolink}.[1] Livsmodeller av dinosaurier som man kan se i ett museum kan också kallas {velqa':n:nolink}.[2] [AUTOTRANSLATED]</column>
    <column name="examples_sv"></column>
    <column name="search_tags_sv"></column>
  </mixin>
  <mixin target="dd2b59dc-55cd-4f36-9344-a4e937e96008">
    <!-- (G) entry_name: velSo' -->
    <!-- (G) part_of_speech: n -->
    <column name="definition_sv">krom [AUTOTRANSLATED]</column>
    <column name="notes_sv">Detta avser elementärt krom, medan {qo'rIn:n} avser kromsalter som de som används i läderbrun. [AUTOTRANSLATED]</column>
    <column name="examples_sv"></column>
    <column name="search_tags_sv"></column>
  </mixin>
  <mixin target="7d21b6ea-4421-44c2-9e20-0bbf83d36eae">
    <!-- (G) entry_name: velSo' 'uSqan -->
    <!-- (G) part_of_speech: n:deriv -->
    <column name="definition_sv">rostfritt stål [AUTOTRANSLATED]</column>
    <column name="notes_sv"></column>
    <column name="examples_sv"></column>
    <column name="search_tags_sv"></column>
  </mixin>
  <mixin target="f009b99f-ceea-4205-83fd-9f15e59a5849">
    <!-- (G) entry_name: vem -->
    <!-- (G) part_of_speech: v:i,klcp1 -->
    <column name="definition_sv">vakna, sluta sova</column>
    <column name="notes_sv"></column>
    <column name="examples_sv"></column>
    <column name="search_tags_sv"></column>
  </mixin>
  <mixin target="347add95-a4b0-4c1a-afa5-4d4e1f2a2c57">
    <!-- (G) entry_name: vemmoH -->
    <!-- (G) part_of_speech: v:t_c,deriv -->
    <column name="definition_sv">väcka (någon)</column>
    <column name="notes_sv"></column>
    <column name="examples_sv"></column>
    <column name="search_tags_sv"></column>
  </mixin>
  <mixin target="5d827342-a46f-446b-a211-cc2c4825eb27">
    <!-- (G) entry_name: vem -->
    <!-- (G) part_of_speech: n -->
    <column name="definition_sv">skriva ut, markera, spåra, spåra, bild, mönster [AUTOTRANSLATED]</column>
    <column name="notes_sv">Detta hänvisar till spåret eller märkena som lämnas efter beröring, till exempel (bilden av) ett fingeravtryck, däckspår eller mönstret i smuts som följer av att kliva på det.

Detta ord kontrasteras med {Su'nIm:n} som hänvisar till mönstret som gör {vem:n:nolink}. Men {Su'nIm:n:nolink} används bara när det är något mycket detaljerat som lämnar {vem:n:nolink}. Jämför till exempel {nItlh Su'nIm:n} "fingeravtryck" (åsar på fingertoppen) med {nItlh Su'nIm vem:n} "fingeravtryck" (markera kvar efter beröring).

Observera att en avsiktligt producerad, stämpelliknande bild är en {yang:n}.

I följande exempel kan det specifika finger- eller tånamnet användas istället för {nItlh:n} (eller {yaD:n:1}). [AUTOTRANSLATED]</column>
    <column name="examples_sv"></column>
    <column name="search_tags_sv"></column>
  </mixin>
  <mixin target="d14280a5-3601-4a96-b444-9e5fc3ff101a">
    <!-- (G) entry_name: vem'eq -->
    <!-- (G) part_of_speech: n:anim -->
    <column name="definition_sv">en slags fågel</column>
    <column name="notes_sv">Detta är en fågel som nästan uteslutande livnär sig på ormormen från vilken {qagh:n} är tillverkad. Klingoner är inte särskilt förtjust i denna fågel. [AUTOTRANSLATED]</column>
    <column name="examples_sv"></column>
    <column name="search_tags_sv"></column>
  </mixin>
  <mixin target="bb612dd0-db85-49a0-a0e1-661dedaef237">
    <!-- (G) entry_name: ven -->
    <!-- (G) part_of_speech: v:is -->
    <column name="definition_sv">vara nördig [AUTOTRANSLATED]</column>
    <column name="notes_sv">Detta ord beskriver någon som verkligen är inne i något (eller ett antal saker), som deltar i aktiviteter som är associerade med det och gör det mycket på allvar. [AUTOTRANSLATED]</column>
    <column name="examples_sv"></column>
    <column name="search_tags_sv"></column>
  </mixin>
  <mixin target="691453a1-94fd-4ce2-a0ba-c2c9c637d0c7">
    <!-- (G) entry_name: venwI' -->
    <!-- (G) part_of_speech: n:being,deriv -->
    <column name="definition_sv">nörd [AUTOTRANSLATED]</column>
    <column name="notes_sv">Detta ord beskriver någon som verkligen är inne i något (eller ett antal saker), som deltar i aktiviteter som är associerade med det och gör det mycket på allvar.

En vanligare term för detta är {qatru':n:nolink}. [AUTOTRANSLATED]</column>
    <column name="examples_sv"></column>
    <column name="search_tags_sv"></column>
  </mixin>
  <mixin target="75c3651f-b708-4485-bdd8-6ea06cb7fab3">
    <!-- (G) entry_name: veng -->
    <!-- (G) part_of_speech: n:klcp1 -->
    <column name="definition_sv">stad</column>
    <column name="notes_sv"></column>
    <column name="examples_sv"></column>
    <column name="search_tags_sv"></column>
  </mixin>
  <mixin target="7c75b8a5-9ff9-40dd-af73-12ac36fb2e16">
    <!-- (G) entry_name: veng wa'DIch -->
    <!-- (G) part_of_speech: n:place,deriv,fic -->
    <column name="definition_sv">Första Staden (Kronos huvudstad)</column>
    <column name="notes_sv"></column>
    <column name="examples_sv"></column>
    <column name="search_tags_sv"></column>
  </mixin>
  <mixin target="1eaf394f-e9f5-41a7-b649-fa93237d47cb">
    <!-- (G) entry_name: veng wa'DIch Sep -->
    <!-- (G) part_of_speech: n:place,deriv,fic -->
    <column name="definition_sv">Första Stads-regionen</column>
    <column name="notes_sv"></column>
    <column name="examples_sv"></column>
    <column name="search_tags_sv"></column>
  </mixin>
  <mixin target="c089d975-a9c7-431c-804a-8a36a195fd47">
    <!-- (G) entry_name: vengHom -->
    <!-- (G) part_of_speech: n:deriv -->
    <column name="definition_sv">by</column>
    <column name="notes_sv"></column>
    <column name="examples_sv"></column>
    <column name="search_tags_sv"></column>
  </mixin>
  <mixin target="3b2dc67c-c45c-4e84-877a-15e6d3fd1462">
    <!-- (G) entry_name: vep -->
    <!-- (G) part_of_speech: n -->
    <column name="definition_sv">proklamation, anmälan, tillkännagivande och liknande [AUTOTRANSLATED]</column>
    <column name="notes_sv"></column>
    <column name="examples_sv"></column>
    <column name="search_tags_sv"></column>
  </mixin>
  <mixin target="2b2e0b7e-b9cf-4c59-b253-1873d927b769">
    <!-- (G) entry_name: veqlargh -->
    <!-- (G) part_of_speech: n:name,fic -->
    <column name="definition_sv">djävul, demon, Fek'lhr</column>
    <column name="notes_sv">Det finns ett formspråk, {qej; veqlargh rur@@qej:v, veqlargh:n, rur:v}. [AUTOTRANSLATED]</column>
    <column name="examples_sv"></column>
    <column name="search_tags_sv"></column>
  </mixin>
  <mixin target="9bd4442b-15f0-4931-802a-9f108a180415">
    <!-- (G) entry_name: veqlarghlI' yIbuS 'ej veqlarghwI' vIbuS. -->
    <!-- (G) part_of_speech: sen:phr -->
    <column name="definition_sv">Du uppmärksammar din Fek'lhr och jag kommer att uppmärksamma mina. [AUTOTRANSLATED]</column>
    <column name="notes_sv"></column>
    <column name="examples_sv"></column>
    <column name="search_tags_sv"></column>
  </mixin>
  <mixin target="ae09edde-59c6-4b64-b1d1-6294069e07dc">
    <!-- (G) entry_name: veqtal -->
    <!-- (G) part_of_speech: n -->
    <column name="definition_sv">VeK'tal svar [AUTOTRANSLATED]</column>
    <column name="notes_sv"></column>
    <column name="examples_sv"></column>
    <column name="search_tags_sv"></column>
  </mixin>
  <mixin target="2d8e5e13-5478-46f4-aaab-dcdbad91042c">
    <!-- (G) entry_name: veQ -->
    <!-- (G) part_of_speech: n:klcp1 -->
    <column name="definition_sv">sopor, avfall</column>
    <column name="notes_sv">Se Gowron säga detta: {YouTube video:url:http://youtu.be/PBM4fiXLc-U} [AUTOTRANSLATED]</column>
    <column name="examples_sv"></column>
    <column name="search_tags_sv"></column>
  </mixin>
  <mixin target="fce1e69c-e2fd-44a4-979c-66d0e1a7d7d9">
    <!-- (G) entry_name: veQDuj -->
    <!-- (G) part_of_speech: n:deriv -->
    <column name="definition_sv">avfallspråm</column>
    <column name="notes_sv"></column>
    <column name="examples_sv"></column>
    <column name="search_tags_sv"></column>
  </mixin>
  <mixin target="45a985b0-9a75-4246-b1f4-e3b8a2b39ece">
    <!-- (G) entry_name: veQDuj 'oH DujlIj'e'. -->
    <!-- (G) part_of_speech: sen:phr -->
    <column name="definition_sv">Ditt skepp är en skräpspår. [AUTOTRANSLATED]</column>
    <column name="notes_sv"></column>
    <column name="examples_sv"></column>
    <column name="search_tags_sv"></column>
  </mixin>
  <mixin target="84b035a2-782c-46b5-92ed-e0397cc396c0">
    <!-- (G) entry_name: ver -->
    <!-- (G) part_of_speech: v:1,is -->
    <column name="definition_sv">vara spiral [AUTOTRANSLATED]</column>
    <column name="notes_sv">Detta ord kan användas för att prata om vinden ({SuS:n}). Till exempel betyder {ver SuS'a':sen@@ver:v:1, SuS:n, -'a':n} "en tornado händer". {ver SuS:sen@@ver:v:1, SuS:n} eller {ver SuSHom:sen@@ver:v:1, SuS:n, -Hom:n} skulle troligtvis hänvisa till en virvelvind. [AUTOTRANSLATED]</column>
    <column name="examples_sv"></column>
    <column name="search_tags_sv"></column>
  </mixin>
  <mixin target="36ad90fe-357e-4c6b-af53-0571033a3f55">
    <!-- (G) entry_name: ver -->
    <!-- (G) part_of_speech: v:2,is -->
    <column name="definition_sv">vara yr, vara snurrig</column>
    <column name="notes_sv"></column>
    <column name="examples_sv"></column>
    <column name="search_tags_sv"></column>
  </mixin>
  <mixin target="b1bc3ec5-7aaa-4888-b4a8-b222faa7b3d0">
    <!-- (G) entry_name: veragh -->
    <!-- (G) part_of_speech: n -->
    <column name="definition_sv">nit</column>
    <column name="notes_sv"></column>
    <column name="examples_sv"></column>
    <column name="search_tags_sv"></column>
  </mixin>
  <mixin target="9effdf76-9d6b-444c-ac06-adaa06555513">
    <!-- (G) entry_name: verengan -->
    <!-- (G) part_of_speech: n:being,deriv,fic -->
    <column name="definition_sv">ferengi</column>
    <column name="notes_sv">Ferengis är kända för sin girighet, vilket återspeglas i jämförelsen {qur; verengan rur@@qur:v, verengan:n, rur:v}. [AUTOTRANSLATED]</column>
    <column name="examples_sv"></column>
    <column name="search_tags_sv"></column>
  </mixin>
  <mixin target="f78e20f6-e64e-4ff0-a6f4-5cea96cb431e">
    <!-- (G) entry_name: verenganar -->
    <!-- (G) part_of_speech: n:place,fic -->
    <column name="definition_sv">Ferenginar</column>
    <column name="notes_sv">Detta är namnet på Ferengi Homeworld, den främsta planeten i Ferengi Alliance. [AUTOTRANSLATED]</column>
    <column name="examples_sv"></column>
    <column name="search_tags_sv"></column>
  </mixin>
  <mixin target="6eb11744-3c94-4132-89ed-d7424c1e2ab9">
    <!-- (G) entry_name: verengan Ha'DIbaH -->
    <!-- (G) part_of_speech: n:deriv -->
    <column name="definition_sv">ferengitölp, ferengihund</column>
    <column name="notes_sv">Se Gowron säga detta: {YouTube video:url:http://youtu.be/8MLXFbHYZOk} [AUTOTRANSLATED]</column>
    <column name="examples_sv"></column>
    <column name="search_tags_sv"></column>
  </mixin>
  <mixin target="0e13ecb2-df96-4df7-ade8-bd09ae81b1c5">
    <!-- (G) entry_name: vergh -->
    <!-- (G) part_of_speech: n -->
    <column name="definition_sv">docka (för skepp)</column>
    <column name="notes_sv">Detta avser en plats med en struktur att fästa ett fartyg till, som en brygga.[2] [AUTOTRANSLATED]</column>
    <column name="examples_sv"></column>
    <column name="search_tags_sv"></column>
  </mixin>
  <mixin target="3a95e91a-4cb8-4ac0-9bae-bdcb15cb9a97">
    <!-- (G) entry_name: vergh -->
    <!-- (G) part_of_speech: v:t_c,klcp1 -->
    <column name="definition_sv">docka, parkera</column>
    <column name="notes_sv">Objektet är fordonet som är dockat.[3]

I {Klingon Monopoly:src} översätts "Free Parking" till {vergh 'ach DIlnISbe':sen:nolink}. [AUTOTRANSLATED]</column>
    <column name="examples_sv"></column>
    <column name="search_tags_sv"></column>
  </mixin>
  <mixin target="27777c9f-7574-43bc-ac9d-e0708980819c">
    <!-- (G) entry_name: veS -->
    <!-- (G) part_of_speech: n -->
    <column name="definition_sv">krig, krigföring (som koncept)</column>
    <column name="notes_sv">Kontrast detta med {noH:n}, som hänvisar till ett specifikt krig.[1, p.47] [AUTOTRANSLATED]</column>
    <column name="examples_sv"></column>
    <column name="search_tags_sv"></column>
  </mixin>
  <mixin target="445bbb7a-a5e0-4ff3-9591-c77dc5771381">
    <!-- (G) entry_name: veSDuj -->
    <!-- (G) part_of_speech: n:deriv -->
    <column name="definition_sv">krigsskepp</column>
    <column name="notes_sv"></column>
    <column name="examples_sv"></column>
    <column name="search_tags_sv"></column>
  </mixin>
  <mixin target="d9fd9fcc-0d3d-4554-ad21-2d6802f0af41">
    <!-- (G) entry_name: veStay -->
    <!-- (G) part_of_speech: n:being -->
    <column name="definition_sv">vestai (rang) [AUTOTRANSLATED]</column>
    <column name="notes_sv">Från lägsta till högsta är dessa rangordningar: {tay:n:3}, {Sutay:n}, {veStay:n:nolink}, {Santay:n}, {'Iptay:n}. [AUTOTRANSLATED]</column>
    <column name="examples_sv"></column>
    <column name="search_tags_sv"></column>
  </mixin>
  <mixin target="894f80ad-1f1f-43bd-befa-89c8bc6e92ab">
    <!-- (G) entry_name: vetlh -->
    <!-- (G) part_of_speech: n:anim -->
    <column name="definition_sv">kackerlacka</column>
    <column name="notes_sv"></column>
    <column name="examples_sv"></column>
    <column name="search_tags_sv"></column>
  </mixin>
  <mixin target="95bd58ca-a9ad-4a55-9697-b33677b32fa6">
    <!-- (G) entry_name: vev -->
    <!-- (G) part_of_speech: v:t_c -->
    <column name="definition_sv">sätt in, sätt in, stift (fäst eller fäst med en stift) [AUTOTRANSLATED]</column>
    <column name="notes_sv">Detta är ett möjligt verb att använda med {watrIn:n}.[3] [AUTOTRANSLATED]</column>
    <column name="examples_sv"></column>
    <column name="search_tags_sv"></column>
  </mixin>
  <mixin target="bb886590-7a43-43b6-8c7c-338912652c5d">
    <!-- (G) entry_name: vey -->
    <!-- (G) part_of_speech: n -->
    <column name="definition_sv">sats, uppsättning, packe, bunt, uppsättning</column>
    <column name="notes_sv"></column>
    <column name="examples_sv"></column>
    <column name="search_tags_sv"></column>
  </mixin>
  <mixin target="9750eff0-8bb4-4374-9153-8479b1f5c340">
    <!-- (G) entry_name: vey' -->
    <!-- (G) part_of_speech: v:is -->
    <column name="definition_sv">var bekväm, var riklig [AUTOTRANSLATED]</column>
    <column name="notes_sv"></column>
    <column name="examples_sv"></column>
    <column name="search_tags_sv"></column>
  </mixin>
  <mixin target="53e36e9d-ec6b-47d8-ad31-818a030183af">
    <!-- (G) entry_name: vey'Ha' -->
    <!-- (G) part_of_speech: v:is,deriv -->
    <column name="definition_sv">vara obekväm, var liten [AUTOTRANSLATED]</column>
    <column name="notes_sv">Detta betyder mer än att inte vara tillräckligt eller otillräckligt (se {yap:v}). [AUTOTRANSLATED]</column>
    <column name="examples_sv"></column>
    <column name="search_tags_sv"></column>
  </mixin>
  <mixin target="a315d1d9-694b-4a53-9273-1b9c8c85ebb3">
    <!-- (G) entry_name: ve' -->
    <!-- (G) part_of_speech: v:t_c -->
    <column name="definition_sv">resa med ett syfte, av en särskild anledning resa på ett uppdrag [AUTOTRANSLATED]</column>
    <column name="notes_sv"></column>
    <column name="examples_sv"></column>
    <column name="search_tags_sv"></column>
  </mixin>
  <mixin target="45cf8420-272f-423b-b672-c7df804ca92c">
    <!-- (G) entry_name: ve'Ha' -->
    <!-- (G) part_of_speech: v:i,deriv -->
    <column name="definition_sv">vara vågig (hår) [AUTOTRANSLATED]</column>
    <column name="notes_sv"></column>
    <column name="examples_sv"></column>
    <column name="search_tags_sv"></column>
  </mixin>
  <mixin target="b5bfcdfb-dc16-4a38-841b-559e952c05ce">
    <!-- (G) entry_name: vI- -->
    <!-- (G) part_of_speech: v:pref,klcp1 -->
    <column name="definition_sv">jag-honom/henne/det/dem</column>
    <column name="notes_sv"></column>
    <column name="examples_sv"></column>
    <column name="search_tags_sv"></column>
  </mixin>
  <mixin target="7159ac83-132d-4ca9-b6c1-ec75af427c19">
    <!-- (G) entry_name: vIb -->
    <!-- (G) part_of_speech: v:1,t_c -->
    <column name="definition_sv">flytta genom tiden mot framtiden [AUTOTRANSLATED]</column>
    <column name="notes_sv"></column>
    <column name="examples_sv"></column>
    <column name="search_tags_sv"></column>
  </mixin>
  <mixin target="8009b820-154f-4273-90ef-a029a4db42c2">
    <!-- (G) entry_name: vIb -->
    <!-- (G) part_of_speech: v:2,t_c -->
    <column name="definition_sv">propagera (inte i referens till växter) [AUTOTRANSLATED]</column>
    <column name="notes_sv"></column>
    <column name="examples_sv"></column>
    <column name="search_tags_sv"></column>
  </mixin>
  <mixin target="9a16de31-f08c-45b8-becf-34c8a4c84813">
    <!-- (G) entry_name: vIbHa' -->
    <!-- (G) part_of_speech: v:t_c,deriv -->
    <column name="definition_sv">flytta genom tiden mot det förflutna [AUTOTRANSLATED]</column>
    <column name="notes_sv"></column>
    <column name="examples_sv"></column>
    <column name="search_tags_sv"></column>
  </mixin>
  <mixin target="8d5d3a6e-d788-4715-92b2-61376dc1ecb9">
    <!-- (G) entry_name: vID -->
    <!-- (G) part_of_speech: v:is -->
    <column name="definition_sv">vara stridslysten, vara stridande, vara krigförande</column>
    <column name="notes_sv"></column>
    <column name="examples_sv"></column>
    <column name="search_tags_sv"></column>
  </mixin>
  <mixin target="9999a36f-2af7-4804-a376-045685b6a6e4">
    <!-- (G) entry_name: vID'Ir -->
    <!-- (G) part_of_speech: n -->
    <column name="definition_sv">baffelplåt, skiljevägg, mellanvägg</column>
    <column name="notes_sv">Detta är en enhet som reglerar flödet av gas, ljud etc. [AUTOTRANSLATED]</column>
    <column name="examples_sv"></column>
    <column name="search_tags_sv"></column>
  </mixin>
  <mixin target="fdbf8798-4201-49b4-b45a-499e9dabacf3">
    <!-- (G) entry_name: vIghro' -->
    <!-- (G) part_of_speech: n:anim -->
    <column name="definition_sv">ett slags djur, v'gro (kattlik)</column>
    <column name="notes_sv"></column>
    <column name="examples_sv"></column>
    <column name="search_tags_sv"></column>
  </mixin>
  <mixin target="6c9b61bb-2ce5-466e-81d0-8a50643da388">
    <!-- (G) entry_name: vIH -->
    <!-- (G) part_of_speech: v:i_c -->
    <column name="definition_sv">röra sig, vara i rörelse</column>
    <column name="notes_sv">Detta verb är intransitivt. För att säga att någon eller något flyttar någon eller något annat, använd {vIHmoH:v:nolink}.[2]

För {taD:v} för ett idiomatiskt uttryck som används för att säga någon att inte flytta. [AUTOTRANSLATED]</column>
    <column name="examples_sv"></column>
    <column name="search_tags_sv"></column>
  </mixin>
  <mixin target="251c9a75-0550-4f7a-b820-18f4af653da5">
    <!-- (G) entry_name: vIHtaH gho -->
    <!-- (G) part_of_speech: sen:idiom -->
    <column name="definition_sv">Hängen rör sig [AUTOTRANSLATED]</column>
    <column name="notes_sv">Detta idiomatiska uttryck betyder att en aktivitet med begränsad (men kanske obestämd) längd har börjat. Det kommer från {qa'vaQ:n}. [AUTOTRANSLATED]</column>
    <column name="examples_sv"></column>
    <column name="search_tags_sv"></column>
  </mixin>
  <mixin target="2fbef440-b09a-4e35-9780-29a1e5c37510">
    <!-- (G) entry_name: vIj -->
    <!-- (G) part_of_speech: n:inhps -->
    <column name="definition_sv">raketmotor, raket</column>
    <column name="notes_sv"></column>
    <column name="examples_sv"></column>
    <column name="search_tags_sv"></column>
  </mixin>
  <mixin target="17883e95-2ab0-41ee-8387-1aa9c0d2014f">
    <!-- (G) entry_name: vIl -->
    <!-- (G) part_of_speech: v:1,is -->
    <column name="definition_sv">vara fårad, vara guppig</column>
    <column name="notes_sv"></column>
    <column name="examples_sv"></column>
    <column name="search_tags_sv"></column>
  </mixin>
  <mixin target="ba320d88-61e0-4738-858d-93e2b30db0f0">
    <!-- (G) entry_name: vIl -->
    <!-- (G) part_of_speech: v:2,is,slang -->
    <column name="definition_sv">var cool (som i chic) [AUTOTRANSLATED]</column>
    <column name="notes_sv"></column>
    <column name="examples_sv"></column>
    <column name="search_tags_sv"></column>
  </mixin>
  <mixin target="83c4ad57-c379-4603-8db9-553de86e443e">
    <!-- (G) entry_name: vIl -->
    <!-- (G) part_of_speech: n -->
    <column name="definition_sv">gupp, bula</column>
    <column name="notes_sv"></column>
    <column name="examples_sv"></column>
    <column name="search_tags_sv"></column>
  </mixin>
  <mixin target="612b2737-3143-450f-b105-918b87d47ba4">
    <!-- (G) entry_name: vIlle' -->
    <!-- (G) part_of_speech: n:being,deriv -->
    <column name="definition_sv">underhuggare, servil tjänare, hantlangare, hejduk</column>
    <column name="notes_sv"></column>
    <column name="examples_sv"></column>
    <column name="search_tags_sv"></column>
  </mixin>
  <mixin target="5614d30c-5283-4289-a802-fe8db2074581">
    <!-- (G) entry_name: vIlHom -->
    <!-- (G) part_of_speech: n:body,deriv -->
    <column name="definition_sv">panna ridge [AUTOTRANSLATED]</column>
    <column name="notes_sv"></column>
    <column name="examples_sv"></column>
    <column name="search_tags_sv"></column>
  </mixin>
  <mixin target="418f7b65-cdc8-4696-bed2-a340c82c75c4">
    <!-- (G) entry_name: vIlInHoD -->
    <!-- (G) part_of_speech: n:anim -->
    <column name="definition_sv">en slags fågel (förmögen att härma språk)</column>
    <column name="notes_sv"></column>
    <column name="examples_sv"></column>
    <column name="search_tags_sv"></column>
  </mixin>
  <mixin target="a734290d-7ed1-4436-b96a-807179c1c1b5">
    <!-- (G) entry_name: vIn -->
    <!-- (G) part_of_speech: n:being -->
    <column name="definition_sv">{lor:n:0} eller {tey':n:0}; kusin, brorsdotter, systerdotter, brorson, systerson</column>
    <column name="notes_sv">I singular föredras typiskt {tey':n:nolink} eller {lor:n:nolink} såvida inte individen hänvisas till som en medlem av en grupp som troligen inkluderar både {tey':n:nolink} och / eller {lor:n:nolink}. Flertalsformen {vInpu':n:nolink} används för en grupp som inkluderar {tey':n:nolink} och / eller {lor:n:nolink}. [AUTOTRANSLATED]</column>
    <column name="examples_sv"></column>
    <column name="search_tags_sv"></column>
  </mixin>
  <mixin target="90c63bf3-5bbf-40cd-8621-7123e35bff99">
    <!-- (G) entry_name: vIncha' -->
    <!-- (G) part_of_speech: n -->
    <column name="definition_sv">ugn [AUTOTRANSLATED]</column>
    <column name="notes_sv"></column>
    <column name="examples_sv"></column>
    <column name="search_tags_sv"></column>
  </mixin>
  <mixin target="be425dc3-d317-4465-9c49-b1eaf9b55229">
    <!-- (G) entry_name: vInDa' -->
    <!-- (G) part_of_speech: n:being -->
    <column name="definition_sv">landsmän, samhällsledamot, kohort, medborgare [AUTOTRANSLATED]</column>
    <column name="notes_sv"></column>
    <column name="examples_sv"></column>
    <column name="search_tags_sv"></column>
  </mixin>
  <mixin target="cb429a15-6a8f-4890-ad05-351f3f9c3d5f">
    <!-- (G) entry_name: vIno'va' qurgh -->
    <!-- (G) part_of_speech: n:food -->
    <column name="definition_sv">finova bönor</column>
    <column name="notes_sv"></column>
    <column name="examples_sv"></column>
    <column name="search_tags_sv"></column>
  </mixin>
  <mixin target="db3d9162-57a3-4e03-bbab-982fc159a718">
    <!-- (G) entry_name: vIng -->
    <!-- (G) part_of_speech: v:t -->
    <column name="definition_sv">gnälla, jämra sig, gny</column>
    <column name="notes_sv"></column>
    <column name="examples_sv"></column>
    <column name="search_tags_sv"></column>
  </mixin>
  <mixin target="75a79623-974a-4b57-be9e-5f7a4165105f">
    <!-- (G) entry_name: vIq -->
    <!-- (G) part_of_speech: n -->
    <column name="definition_sv">slag, strid (som koncept)</column>
    <column name="notes_sv">Detta ord hänvisar till det abstrakta begreppet strid. En specifik strid är en {may':n}. [AUTOTRANSLATED]</column>
    <column name="examples_sv"></column>
    <column name="search_tags_sv"></column>
  </mixin>
  <mixin target="b5258d36-a088-4cb9-ae00-6da5bedb17f7">
    <!-- (G) entry_name: vIqraq -->
    <!-- (G) part_of_speech: n -->
    <column name="definition_sv">artefakt, konstverk [AUTOTRANSLATED]</column>
    <column name="notes_sv">Denna term är mer allmän än ett visuellt konstverk. Det täcker det, men också en artefakt (inte i arkeologisk mening), hantverk, gizmo, gadget, kontraption, maskin, anordning etc. Det vill säga det hänvisar till något tillverkat eller tillverkat.[1] av ett företag (om produkten var fysisk).[2] [AUTOTRANSLATED]</column>
    <column name="examples_sv"></column>
    <column name="search_tags_sv"></column>
  </mixin>
  <mixin target="074a29e4-8d0b-4f64-b689-3897b5b4323a">
    <!-- (G) entry_name: vIqSIS -->
    <!-- (G) part_of_speech: n:name,fic -->
    <column name="definition_sv">Vixis</column>
    <column name="notes_sv"></column>
    <column name="examples_sv"></column>
    <column name="search_tags_sv"></column>
  </mixin>
  <mixin target="00d85294-96df-4c18-865f-ea0dc0c977f8">
    <!-- (G) entry_name: vIQ -->
    <!-- (G) part_of_speech: v:i_c -->
    <column name="definition_sv">kväva [AUTOTRANSLATED]</column>
    <column name="notes_sv">Detta innebär att man berövas luft. För "drunkna", föregå verbet med {bIQDaq:sen@@bIQ:n, -Daq:n} eller liknande. [AUTOTRANSLATED]</column>
    <column name="examples_sv"></column>
    <column name="search_tags_sv"></column>
  </mixin>
  <mixin target="14da6356-0167-4cc5-818e-11116440f26d">
    <!-- (G) entry_name: vIQmoH -->
    <!-- (G) part_of_speech: v:t_c,deriv -->
    <column name="definition_sv">kväva [AUTOTRANSLATED]</column>
    <column name="notes_sv">Detta innebär att få någon / något att berövas luft. För "drunkna", föregå verbet med {bIQDaq:sen@@bIQ:n, -Daq:n} eller liknande. [AUTOTRANSLATED]</column>
    <column name="examples_sv"></column>
    <column name="search_tags_sv"></column>
  </mixin>
  <mixin target="9bfa0da4-89e4-46ce-99ac-6c36b748af1f">
    <!-- (G) entry_name: vIrgh -->
    <!-- (G) part_of_speech: v:t_c -->
    <column name="definition_sv">rippa (upp), snedstreck, riva (upp), krossa [AUTOTRANSLATED]</column>
    <column name="notes_sv">Till exempel skulle detta användas för att rippa ett foto i hälften. [AUTOTRANSLATED]</column>
    <column name="examples_sv"></column>
    <column name="search_tags_sv"></column>
  </mixin>
  <mixin target="3491d135-b1c1-4c93-9061-669d7eadd559">
    <!-- (G) entry_name: vIrveq -->
    <!-- (G) part_of_speech: n -->
    <column name="definition_sv">terrorism [AUTOTRANSLATED]</column>
    <column name="notes_sv"></column>
    <column name="examples_sv"></column>
    <column name="search_tags_sv"></column>
  </mixin>
  <mixin target="b53d1e48-97c6-46be-86bd-284d2c29cfaa">
    <!-- (G) entry_name: vISeHmeH Hoch nuHmey Qay! -->
    <!-- (G) part_of_speech: sen:phr -->
    <column name="definition_sv">Alla vapen till min kontroll! [AUTOTRANSLATED]</column>
    <column name="notes_sv"></column>
    <column name="examples_sv"></column>
    <column name="search_tags_sv"></column>
  </mixin>
  <mixin target="349a209e-fb1f-4eca-ad25-71d3b273930b">
    <!-- (G) entry_name: vIt -->
    <!-- (G) part_of_speech: v:t,klcp1 -->
    <column name="definition_sv">säga sanningen</column>
    <column name="notes_sv"></column>
    <column name="examples_sv"></column>
    <column name="search_tags_sv"></column>
  </mixin>
  <mixin target="040d4803-44b8-48dc-b8b8-a55f27e17b94">
    <!-- (G) entry_name: vIt -->
    <!-- (G) part_of_speech: n -->
    <column name="definition_sv">sanning</column>
    <column name="notes_sv"></column>
    <column name="examples_sv"></column>
    <column name="search_tags_sv"></column>
  </mixin>
  <mixin target="142c7539-9925-4034-8279-5b287ce76add">
    <!-- (G) entry_name: vIta'pu'be'. -->
    <!-- (G) part_of_speech: sen:phr -->
    <column name="definition_sv">Jag gjorde det inte. [AUTOTRANSLATED]</column>
    <column name="notes_sv"></column>
    <column name="examples_sv"></column>
    <column name="search_tags_sv"></column>
  </mixin>
  <mixin target="ba031e67-e24c-44b3-a328-96dc4f1c6d72">
    <!-- (G) entry_name: vItHay' -->
    <!-- (G) part_of_speech: n -->
    <column name="definition_sv">sanningstestet</column>
    <column name="notes_sv"></column>
    <column name="examples_sv"></column>
    <column name="search_tags_sv"></column>
  </mixin>
  <mixin target="d11667d3-a769-4345-b2e6-dbd37d226846">
    <!-- (G) entry_name: vIttlhegh -->
    <!-- (G) part_of_speech: n:deriv -->
    <column name="definition_sv">talesätt, ordspråk</column>
    <column name="notes_sv"></column>
    <column name="examples_sv"></column>
    <column name="search_tags_sv"></column>
  </mixin>
  <mixin target="78d5ed80-ea7a-4040-a1a1-235a1f0243d2">
    <!-- (G) entry_name: vItlh -->
    <!-- (G) part_of_speech: v:is -->
    <column name="definition_sv">vara hög, stor (i kvantitet, storlek, intensitet) [AUTOTRANSLATED]</column>
    <column name="notes_sv">Detta används för saker som är mätbara eller kvantifierbara, men inte nödvändigtvis räknbara. För räknbara saker skulle {law':v} normalt användas, men {vItlh:v:nolink} skulle användas om antalet är högre än normalt eller större än tidigare eller större än vad som förväntades.[3] [AUTOTRANSLATED]</column>
    <column name="examples_sv"></column>
    <column name="search_tags_sv"></column>
  </mixin>
  <mixin target="48d3f1e5-d3e5-4837-832d-8e84cb2178e7">
    <!-- (G) entry_name: vIychorgh -->
    <!-- (G) part_of_speech: n:food -->
    <column name="definition_sv">juice, saft ifrån en växt</column>
    <column name="notes_sv">Detta är vilken vätska som helst från en växt. I vissa regionala dialekter används detta ord för alla vätskor som följer mat. [AUTOTRANSLATED]</column>
    <column name="examples_sv"></column>
    <column name="search_tags_sv"></column>
  </mixin>
  <mixin target="2517c508-2b74-4a78-8621-4872a5759b37">
    <!-- (G) entry_name: vI' -->
    <!-- (G) part_of_speech: v:i_c -->
    <column name="definition_sv">ackumulera, samlas, lagra upp</column>
    <column name="notes_sv">Örvax (se {Serrum:n}) sägs göra detta i örat.[2] [AUTOTRANSLATED]</column>
    <column name="examples_sv"></column>
    <column name="search_tags_sv"></column>
  </mixin>
  <mixin target="f5f68783-a99e-437f-bba1-19269d3ffa40">
    <!-- (G) entry_name: vI' -->
    <!-- (G) part_of_speech: n:1 -->
    <column name="definition_sv">skjutfärdighet, träffsäkerhet</column>
    <column name="notes_sv"></column>
    <column name="examples_sv"></column>
    <column name="search_tags_sv"></column>
  </mixin>
  <mixin target="085b8cc7-623a-40b2-ac20-4999af60a05c">
    <!-- (G) entry_name: vI' -->
    <!-- (G) part_of_speech: n:2 -->
    <column name="definition_sv">decimalpunkt</column>
    <column name="notes_sv"></column>
    <column name="examples_sv"></column>
    <column name="search_tags_sv"></column>
  </mixin>
  <mixin target="af71d755-da85-4694-aeaa-d986364293a1">
    <!-- (G) entry_name: vI'Hop -->
    <!-- (G) part_of_speech: n -->
    <column name="definition_sv">indirekt objekt [AUTOTRANSLATED]</column>
    <column name="notes_sv">Detta är en grammatisk term. [AUTOTRANSLATED]</column>
    <column name="examples_sv"></column>
    <column name="search_tags_sv"></column>
  </mixin>
  <mixin target="b91c2422-3adc-426e-b2b8-297c331ec8e8">
    <!-- (G) entry_name: vI'Ir -->
    <!-- (G) part_of_speech: n -->
    <column name="definition_sv">tidvatten [AUTOTRANSLATED]</column>
    <column name="notes_sv"></column>
    <column name="examples_sv"></column>
    <column name="search_tags_sv"></column>
  </mixin>
  <mixin target="d5d4f9c2-d763-4011-883d-b64865e58b2f">
    <!-- (G) entry_name: vI'laS -->
    <!-- (G) part_of_speech: n -->
    <column name="definition_sv">dimma, dimma [AUTOTRANSLATED]</column>
    <column name="notes_sv"></column>
    <column name="examples_sv"></column>
    <column name="search_tags_sv"></column>
  </mixin>
  <mixin target="4c935979-0dc7-4d4c-a63a-7ba8bdf362c7">
    <!-- (G) entry_name: voD -->
    <!-- (G) part_of_speech: v:t_c -->
    <column name="definition_sv">borra, borra [AUTOTRANSLATED]</column>
    <column name="notes_sv"></column>
    <column name="examples_sv"></column>
    <column name="search_tags_sv"></column>
  </mixin>
  <mixin target="164791d5-fa4e-486f-9411-5f01c90f3b4e">
    <!-- (G) entry_name: voD jan -->
    <!-- (G) part_of_speech: n:alt,deriv -->
    <column name="definition_sv">{voDmeH jan:n}</column>
    <column name="notes_sv">Detta är en förkortad version av {voDmeH jan:n} som ofta hörs. [AUTOTRANSLATED]</column>
    <column name="examples_sv"></column>
    <column name="search_tags_sv"></column>
  </mixin>
  <mixin target="0e32a758-2b8f-4e96-a6dd-fcae29c6e8da">
    <!-- (G) entry_name: voDmeH jan -->
    <!-- (G) part_of_speech: n:deriv -->
    <column name="definition_sv">borra [AUTOTRANSLATED]</column>
    <column name="notes_sv">Detta avser hela enheten, inte bara borrkronan. Detta förkortas ofta till {voD jan:n}. [AUTOTRANSLATED]</column>
    <column name="examples_sv"></column>
    <column name="search_tags_sv"></column>
  </mixin>
  <mixin target="e5aebe28-24c6-4c6f-b7e7-a42eed7bb9a1">
    <!-- (G) entry_name: voDchuch -->
    <!-- (G) part_of_speech: n:anim -->
    <column name="definition_sv">spindelliknande varelse [AUTOTRANSLATED]</column>
    <column name="notes_sv">Detta är en spindelliknande varelse med nio ben, men ibland sju eller åtta (och inte färre än sju såvida den inte är skadad).

En stor spindel på jorden skulle vara en {tera' voDchuch:n@@tera':n, voDchuch:n}, men en liten spindel skulle inte vara en {voDchuch:n:nolink}. [AUTOTRANSLATED]</column>
    <column name="examples_sv"></column>
    <column name="search_tags_sv"></column>
  </mixin>
  <mixin target="e186ac5a-66d4-4a18-b4c7-746fcfa5149d">
    <!-- (G) entry_name: voDleH -->
    <!-- (G) part_of_speech: n:being -->
    <column name="definition_sv">kejsare</column>
    <column name="notes_sv"></column>
    <column name="examples_sv"></column>
    <column name="search_tags_sv"></column>
  </mixin>
  <mixin target="58013701-ddd6-46cb-8bb4-ab9b52a306ee">
    <!-- (G) entry_name: voDleH Ha'DIbaH -->
    <!-- (G) part_of_speech: n:deriv -->
    <column name="definition_sv">kejsarens kött [AUTOTRANSLATED]</column>
    <column name="notes_sv">Detta avser kött framställt av {HaH:v:2}. Ordet för det specifika köttet ersätter ordet {Ha'DIbaH:n:1}. [AUTOTRANSLATED]</column>
    <column name="examples_sv"></column>
    <column name="search_tags_sv"></column>
  </mixin>
  <mixin target="cfab9297-fabc-49a8-adca-f5a776a4a670">
    <!-- (G) entry_name: vogh -->
    <!-- (G) part_of_speech: n:klcp1 -->
    <column name="definition_sv">någonstans, någon plats</column>
    <column name="notes_sv">När det används som lokativ följs inte detta ord av det lokativa suffixet {-Daq:n:suff}.[3] [AUTOTRANSLATED]</column>
    <column name="examples_sv"></column>
    <column name="search_tags_sv"></column>
  </mixin>
  <mixin target="1418a77b-bbdc-4739-b188-1bc1e4a31636">
    <!-- (G) entry_name: voHDajbo' -->
    <!-- (G) part_of_speech: n -->
    <column name="definition_sv">lösensumma</column>
    <column name="notes_sv">Detta ord kan vara objektet för {wel:v}. [AUTOTRANSLATED]</column>
    <column name="examples_sv"></column>
    <column name="search_tags_sv"></column>
  </mixin>
  <mixin target="aae5a3da-2ba7-41a1-9c6c-aa9e383c66a7">
    <!-- (G) entry_name: voHDajbo' qav'ap -->
    <!-- (G) part_of_speech: n:deriv -->
    <column name="definition_sv">bostadsvärde [AUTOTRANSLATED]</column>
    <column name="notes_sv">Detta ord används i {Klingon Monopoly:src} för att beteckna hur många {QaS:n:1h} spelaren får för att belåna en planet till banken. [AUTOTRANSLATED]</column>
    <column name="examples_sv"></column>
    <column name="search_tags_sv"></column>
  </mixin>
  <mixin target="495e6f07-fa5f-46d5-8104-784b89093d13">
    <!-- (G) entry_name: vol -->
    <!-- (G) part_of_speech: n -->
    <column name="definition_sv">ruta, panel, ark (inte för säng) [AUTOTRANSLATED]</column>
    <column name="notes_sv">Detta är en term relaterad till konstverk. [AUTOTRANSLATED]</column>
    <column name="examples_sv"></column>
    <column name="search_tags_sv"></column>
  </mixin>
  <mixin target="06da365a-d9e4-42ba-a951-aca1029d22fa">
    <!-- (G) entry_name: volchaH -->
    <!-- (G) part_of_speech: n:body -->
    <column name="definition_sv">skuldra, axel</column>
    <column name="notes_sv"></column>
    <column name="examples_sv"></column>
    <column name="search_tags_sv"></column>
  </mixin>
  <mixin target="67f3412b-533e-49bc-8aab-b2d3696557bb">
    <!-- (G) entry_name: von -->
    <!-- (G) part_of_speech: v:t_c -->
    <column name="definition_sv">snara, snärja, fånga (i fälla), förleda, lura</column>
    <column name="notes_sv"></column>
    <column name="examples_sv"></column>
    <column name="search_tags_sv"></column>
  </mixin>
  <mixin target="60b23ce7-de3d-406d-a7ce-83325e927a20">
    <!-- (G) entry_name: vonlu' -->
    <!-- (G) part_of_speech: v:t_c,deriv,slang -->
    <column name="definition_sv">misslyckas totalt</column>
    <column name="notes_sv">Detta slangbegrep används inte som referens till spel utan tillämpas endast på allvarligare frågor.[1, p.165] [AUTOTRANSLATED]</column>
    <column name="examples_sv"></column>
    <column name="search_tags_sv"></column>
  </mixin>
  <mixin target="73298841-cfc5-4e58-b63d-d5fd071a316b">
    <!-- (G) entry_name: vong -->
    <!-- (G) part_of_speech: v:t_c -->
    <column name="definition_sv">hypnotisera</column>
    <column name="notes_sv"></column>
    <column name="examples_sv"></column>
    <column name="search_tags_sv"></column>
  </mixin>
  <mixin target="01ed986d-1e85-48f7-8918-43907a28df85">
    <!-- (G) entry_name: voq -->
    <!-- (G) part_of_speech: v:t_c,klcp1 -->
    <column name="definition_sv">lita på, tro på, ha tillit till</column>
    <column name="notes_sv"></column>
    <column name="examples_sv"></column>
    <column name="search_tags_sv"></column>
  </mixin>
  <mixin target="1bd593db-54a7-4b05-8c48-59460f835512">
    <!-- (G) entry_name: voqHa' -->
    <!-- (G) part_of_speech: v:t_c,deriv -->
    <column name="definition_sv">misstro, inte lita på</column>
    <column name="notes_sv"></column>
    <column name="examples_sv"></column>
    <column name="search_tags_sv"></column>
  </mixin>
  <mixin target="f5336461-84ab-480d-8349-b30ab9178b1e">
    <!-- (G) entry_name: voq -->
    <!-- (G) part_of_speech: n:name,fic -->
    <column name="definition_sv">Voq [AUTOTRANSLATED]</column>
    <column name="notes_sv">Voq var en utstationerad som hänvisade till sig själv som "son of none" ({pagh puqloD:n@@pagh:n:1, puqloD:n}). Han är en följare av {tIquvma:n:name} och fick rollen som {Sech qengwI':n} efter {rej'aq:n:name} död. Han är en albino, vars hudfärg beskrivs som {Dem:v}. [AUTOTRANSLATED]</column>
    <column name="examples_sv"></column>
    <column name="search_tags_sv"></column>
  </mixin>
  <mixin target="cfafafc5-b19d-41a4-a62e-c7f828fa0152">
    <!-- (G) entry_name: voQ -->
    <!-- (G) part_of_speech: v:i_c -->
    <column name="definition_sv">kväva, kvävas, strypa, strypas, få något i halsen</column>
    <column name="notes_sv"></column>
    <column name="examples_sv"></column>
    <column name="search_tags_sv"></column>
  </mixin>
  <mixin target="72dc8367-ab53-4cd3-8859-62d25f00f24c">
    <!-- (G) entry_name: voQSIp -->
    <!-- (G) part_of_speech: n -->
    <column name="definition_sv">kväve</column>
    <column name="notes_sv">Detta ord verkar bestå av verbet {voQ:v} (eller en homofon men okänd substantiv) och {SIp:n}, så det betyder något som "kvävande gas". [AUTOTRANSLATED]</column>
    <column name="examples_sv"></column>
    <column name="search_tags_sv"></column>
  </mixin>
  <mixin target="495c77ed-a23f-4acc-99a7-52eaf7b0f7e3">
    <!-- (G) entry_name: vor -->
    <!-- (G) part_of_speech: v:t_c -->
    <column name="definition_sv">hela, bota</column>
    <column name="notes_sv"></column>
    <column name="examples_sv"></column>
    <column name="search_tags_sv"></column>
  </mixin>
  <mixin target="4def055f-0b19-46b3-9823-8b21a359d3a3">
    <!-- (G) entry_name: vorcha' -->
    <!-- (G) part_of_speech: n:fic -->
    <column name="definition_sv">Vor'cha (ett skepp)</column>
    <column name="notes_sv">Det är oklart varför Federation Standard förstörde stavningen av detta ord genom att flytta {qaghwI':n}. [AUTOTRANSLATED]</column>
    <column name="examples_sv"></column>
    <column name="search_tags_sv"></column>
  </mixin>
  <mixin target="6192252f-a181-430f-8e38-131702940e95">
    <!-- (G) entry_name: vorgh -->
    <!-- (G) part_of_speech: v:is -->
    <column name="definition_sv">vara tidigare [AUTOTRANSLATED]</column>
    <column name="notes_sv">Man kan också använda {nungbogh:v@@nung:v, -bogh:v}. [AUTOTRANSLATED]</column>
    <column name="examples_sv"></column>
    <column name="search_tags_sv"></column>
  </mixin>
  <mixin target="5f851ba0-1809-4dd9-97ee-86aa819c79e2">
    <!-- (G) entry_name: voSpegh Sep -->
    <!-- (G) part_of_speech: n:place,fic -->
    <column name="definition_sv">Vospeg-regionen</column>
    <column name="notes_sv"></column>
    <column name="examples_sv"></column>
    <column name="search_tags_sv"></column>
  </mixin>
  <mixin target="027427cc-f18a-4d73-8b82-92165fd72e36">
    <!-- (G) entry_name: votlh -->
    <!-- (G) part_of_speech: v:is -->
    <column name="definition_sv">vara narcissistisk [AUTOTRANSLATED]</column>
    <column name="notes_sv"></column>
    <column name="examples_sv"></column>
    <column name="search_tags_sv"></column>
  </mixin>
  <mixin target="6fb78afb-5425-43b3-9f81-4e3be545c674">
    <!-- (G) entry_name: vov -->
    <!-- (G) part_of_speech: v:t_c -->
    <column name="definition_sv">gripa, brottas, tussla [AUTOTRANSLATED]</column>
    <column name="notes_sv">För "tackling", kombineras med {pummoH:v@@pum:v:2, -moH:v} "orsak att falla (ner)". [AUTOTRANSLATED]</column>
    <column name="examples_sv"></column>
    <column name="search_tags_sv"></column>
  </mixin>
  <mixin target="3f9cdfca-4313-4795-b236-182ed49f42cf">
    <!-- (G) entry_name: voveng -->
    <!-- (G) part_of_speech: n:body -->
    <column name="definition_sv">körtel [AUTOTRANSLATED]</column>
    <column name="notes_sv"></column>
    <column name="examples_sv"></column>
    <column name="search_tags_sv"></column>
  </mixin>
  <mixin target="bc1addd6-106a-4333-b4e2-5e46206a894e">
    <!-- (G) entry_name: vo' -->
    <!-- (G) part_of_speech: v:t_c -->
    <column name="definition_sv">driva fram</column>
    <column name="notes_sv"></column>
    <column name="examples_sv"></column>
    <column name="search_tags_sv"></column>
  </mixin>
  <mixin target="2b10468b-e44c-49b3-98d1-dae60c8508ea">
    <!-- (G) entry_name: vo'nung -->
    <!-- (G) part_of_speech: n -->
    <column name="definition_sv">fas (fysik) [AUTOTRANSLATED]</column>
    <column name="notes_sv"></column>
    <column name="examples_sv"></column>
    <column name="search_tags_sv"></column>
  </mixin>
  <mixin target="5986573f-7e13-4b67-b699-e220d3174c41">
    <!-- (G) entry_name: vo'yajer -->
    <!-- (G) part_of_speech: n:name,fic -->
    <column name="definition_sv">Voyager [AUTOTRANSLATED]</column>
    <column name="notes_sv">Detta är namnet på ett Federation-rymdskepp. [AUTOTRANSLATED]</column>
    <column name="examples_sv"></column>
    <column name="search_tags_sv"></column>
  </mixin>
  <mixin target="a646746c-9025-4b07-90a0-5b643352bdda">
    <!-- (G) entry_name: vub -->
    <!-- (G) part_of_speech: n:being -->
    <column name="definition_sv">gisslan</column>
    <column name="notes_sv"></column>
    <column name="examples_sv"></column>
    <column name="search_tags_sv"></column>
  </mixin>
  <mixin target="85a09c24-246a-4eab-8bb8-608ddbf81029">
    <!-- (G) entry_name: vubpu' jon nuchpu'. jonbe' tlhInganpu'. -->
    <!-- (G) part_of_speech: sen:phr -->
    <column name="definition_sv">Cowards tar gisslan. Klingons gör det inte. [AUTOTRANSLATED]</column>
    <column name="notes_sv"></column>
    <column name="examples_sv"></column>
    <column name="search_tags_sv"></column>
  </mixin>
  <mixin target="22cfcd2f-22b1-4243-a634-f3f6726c95d3">
    <!-- (G) entry_name: vuD -->
    <!-- (G) part_of_speech: n:klcp1 -->
    <column name="definition_sv">åsikt</column>
    <column name="notes_sv"></column>
    <column name="examples_sv"></column>
    <column name="search_tags_sv"></column>
  </mixin>
  <mixin target="ec87459f-4458-4bd0-aa0c-b15837fc8940">
    <!-- (G) entry_name: vuj -->
    <!-- (G) part_of_speech: v:t_c -->
    <column name="definition_sv">utvisa, skjuta ut [AUTOTRANSLATED]</column>
    <column name="notes_sv">Detta verb kan användas med {turmIq:n}, {qeQ:n} och {taQbang:n:2}. [AUTOTRANSLATED]</column>
    <column name="examples_sv"></column>
    <column name="search_tags_sv"></column>
  </mixin>
  <mixin target="fc81026a-fb0c-45c7-97c9-ce8372e8f4b5">
    <!-- (G) entry_name: vul -->
    <!-- (G) part_of_speech: v:is -->
    <column name="definition_sv">vara medvetslös</column>
    <column name="notes_sv"></column>
    <column name="examples_sv"></column>
    <column name="search_tags_sv"></column>
  </mixin>
  <mixin target="68c18a8e-c63b-475f-904a-d0b48710aa6d">
    <!-- (G) entry_name: vulchoHbe' tlhInganpu'. -->
    <!-- (G) part_of_speech: sen:phr -->
    <column name="definition_sv">Klingoner svimmade inte. [AUTOTRANSLATED]</column>
    <column name="notes_sv"></column>
    <column name="examples_sv"></column>
    <column name="search_tags_sv"></column>
  </mixin>
  <mixin target="7a887f52-431f-4812-9ef9-1590f2554339">
    <!-- (G) entry_name: vulqan -->
    <!-- (G) part_of_speech: n:place,fic,klcp1 -->
    <column name="definition_sv">Vulcan (planet)</column>
    <column name="notes_sv">En planet i federationen. [AUTOTRANSLATED]</column>
    <column name="examples_sv"></column>
    <column name="search_tags_sv"></column>
  </mixin>
  <mixin target="05bb2f32-91c2-4875-982e-93c72b34b6b5">
    <!-- (G) entry_name: vulqangan -->
    <!-- (G) part_of_speech: n:being,deriv,fic,klcp1 -->
    <column name="definition_sv">vulcanit</column>
    <column name="notes_sv"></column>
    <column name="examples_sv"></column>
    <column name="search_tags_sv"></column>
  </mixin>
  <mixin target="417b3105-6fcd-4de9-8c76-da8c15defcdc">
    <!-- (G) entry_name: vum -->
    <!-- (G) part_of_speech: v:t,klcp1 -->
    <column name="definition_sv">arbeta, streta, slita, jobba</column>
    <column name="notes_sv"></column>
    <column name="examples_sv"></column>
    <column name="search_tags_sv"></column>
  </mixin>
  <mixin target="8677dd16-0709-441a-8e6d-7c0fb7c7b0c3">
    <!-- (G) entry_name: vum -->
    <!-- (G) part_of_speech: n:being -->
    <column name="definition_sv">föraktig eller avskyvärd person, scumbag, bastard [AUTOTRANSLATED]</column>
    <column name="notes_sv"></column>
    <column name="examples_sv"></column>
    <column name="search_tags_sv"></column>
  </mixin>
  <mixin target="cc10dc6d-8038-4bc8-a050-197ec1b58a52">
    <!-- (G) entry_name: vun -->
    <!-- (G) part_of_speech: v:t_c -->
    <column name="definition_sv">beställning (i en restaurang, från en katalog, etc.) [AUTOTRANSLATED]</column>
    <column name="notes_sv"></column>
    <column name="examples_sv"></column>
    <column name="search_tags_sv"></column>
  </mixin>
  <mixin target="75b956f8-b08e-40c1-b8e0-318b579d109a">
    <!-- (G) entry_name: vung -->
    <!-- (G) part_of_speech: v:i -->
    <column name="definition_sv">cyklon, orkan [AUTOTRANSLATED]</column>
    <column name="notes_sv">Observera att detta är ett verb i Klingon. I Klingon säger man "det orkaner", liknande det man säger "det regnar" på engelska. [AUTOTRANSLATED]</column>
    <column name="examples_sv"></column>
    <column name="search_tags_sv"></column>
  </mixin>
  <mixin target="c441917a-6f33-4812-aa2f-6b84bfa9e5cb">
    <!-- (G) entry_name: vup -->
    <!-- (G) part_of_speech: v:t_c -->
    <column name="definition_sv">tycka synd om, ha medlidande med, beklaga</column>
    <column name="notes_sv"></column>
    <column name="examples_sv"></column>
    <column name="search_tags_sv"></column>
  </mixin>
  <mixin target="ac385111-e991-40b1-82c3-49da2aac7a92">
    <!-- (G) entry_name: vuQ -->
    <!-- (G) part_of_speech: v:t -->
    <column name="definition_sv">fascinera</column>
    <column name="notes_sv"></column>
    <column name="examples_sv"></column>
    <column name="search_tags_sv"></column>
  </mixin>
  <mixin target="007d5413-1c14-4260-bc91-5723ab9c6f3a">
    <!-- (G) entry_name: vur -->
    <!-- (G) part_of_speech: v:is -->
    <column name="definition_sv">vara modern, aktuell, state-of-the-art [AUTOTRANSLATED]</column>
    <column name="notes_sv"></column>
    <column name="examples_sv"></column>
    <column name="search_tags_sv"></column>
  </mixin>
  <mixin target="a9285231-f714-4659-a73c-a3bb5d8f3a4c">
    <!-- (G) entry_name: vuS -->
    <!-- (G) part_of_speech: v:t_c -->
    <column name="definition_sv">begränsa</column>
    <column name="notes_sv"></column>
    <column name="examples_sv"></column>
    <column name="search_tags_sv"></column>
  </mixin>
  <mixin target="9b510a26-40b9-48cb-b5de-d4da4f420276">
    <!-- (G) entry_name: vut -->
    <!-- (G) part_of_speech: v:t_c,klcp1 -->
    <column name="definition_sv">tilllaga, förbereda, göra (mat och dryck)</column>
    <column name="notes_sv"></column>
    <column name="examples_sv"></column>
    <column name="search_tags_sv"></column>
  </mixin>
  <mixin target="fb55fdf8-3123-4b31-9b3a-e3fd1c21bf84">
    <!-- (G) entry_name: vutmeH 'un -->
    <!-- (G) part_of_speech: n:deriv,reg -->
    <column name="definition_sv">flatbottnad skål för matberedning</column>
    <column name="notes_sv">Ibland förkortas detta till {vut'un:n}. [AUTOTRANSLATED]</column>
    <column name="examples_sv"></column>
    <column name="search_tags_sv"></column>
  </mixin>
  <mixin target="f1ed3883-2c10-4a81-bcc3-045cf2429314">
    <!-- (G) entry_name: vutpa' -->
    <!-- (G) part_of_speech: n -->
    <column name="definition_sv">kök, kabyss</column>
    <column name="notes_sv">Detta avser en plats där mat tillagas. [AUTOTRANSLATED]</column>
    <column name="examples_sv"></column>
    <column name="search_tags_sv"></column>
  </mixin>
  <mixin target="263cb5a1-db00-4979-b5cf-5c380353ac81">
    <!-- (G) entry_name: vutwI' -->
    <!-- (G) part_of_speech: n:being,deriv -->
    <column name="definition_sv">kock, köksa</column>
    <column name="notes_sv"></column>
    <column name="examples_sv"></column>
    <column name="search_tags_sv"></column>
  </mixin>
  <mixin target="3f545933-196d-4bfc-92a6-e79c3f77768c">
    <!-- (G) entry_name: vutwI' quv -->
    <!-- (G) part_of_speech: n:being,deriv -->
    <column name="definition_sv">kökschef [AUTOTRANSLATED]</column>
    <column name="notes_sv"></column>
    <column name="examples_sv"></column>
    <column name="search_tags_sv"></column>
  </mixin>
  <mixin target="2e36ad35-7c2d-4616-921f-52040de70628">
    <!-- (G) entry_name: vut'un -->
    <!-- (G) part_of_speech: n:reg -->
    <column name="definition_sv">flatbottnad skål för matberedning</column>
    <column name="notes_sv">Detta är förkortat för {vutmeH 'un:n}. [AUTOTRANSLATED]</column>
    <column name="examples_sv"></column>
    <column name="search_tags_sv"></column>
  </mixin>
  <mixin target="77dd6838-8b46-4222-b59b-b4ca96c1d5c4">
    <!-- (G) entry_name: vuv -->
    <!-- (G) part_of_speech: v:t_c,klcp1 -->
    <column name="definition_sv">respektera</column>
    <column name="notes_sv"></column>
    <column name="examples_sv"></column>
    <column name="search_tags_sv"></column>
  </mixin>
  <mixin target="2fb81dc1-ed03-43f0-9e52-803dc0ac9734">
    <!-- (G) entry_name: vuy -->
    <!-- (G) part_of_speech: v:i_c -->
    <column name="definition_sv">vara hjälpsam, stödjande [AUTOTRANSLATED]</column>
    <column name="notes_sv"></column>
    <column name="examples_sv"></column>
    <column name="search_tags_sv"></column>
  </mixin>
  <mixin target="e7f4bbcd-6ced-43b3-b469-bf159b841656">
    <!-- (G) entry_name: vu' -->
    <!-- (G) part_of_speech: v:t_c -->
    <column name="definition_sv">sköta, handha, ordna, få bukt med</column>
    <column name="notes_sv"></column>
    <column name="examples_sv"></column>
    <column name="search_tags_sv"></column>
  </mixin>
  <mixin target="1584310c-c750-41e5-a56e-e6cc29de930c">
    <!-- (G) entry_name: vu'wI' -->
    <!-- (G) part_of_speech: n:being,deriv -->
    <column name="definition_sv">direktör, föreståndare, chef, förvaltare</column>
    <column name="notes_sv"></column>
    <column name="examples_sv"></column>
    <column name="search_tags_sv"></column>
  </mixin>
</mixins>
